<?xml version="1.0" encoding="ISO-8859-1"?>
<instrumentType>

  <name>ArtStiffness</name>
  <instrument>
    <name>SphygmoCor 1</name>
    <vendor>AtCor Medical</vendor>
    <model>SphygmoCor</model>
    <serialNumber>01400</serialNumber>
    <barcode>sphygmoCor1</barcode>
    <status>ACTIVE</status>
  </instrument>

  <contraindications>
    <contraIndication>
      <code>Other_CI</code>
      <requiresDescription>true</requiresDescription>
      <type>OBSERVED</type>
    </contraIndication>
  </contraindications>

  <instrumentParameters>
    <input id="id">
      <code>INPUT_PARTICIPANT_BARCODE</code>
      <dataType>TEXT</dataType>
      <captureMethod>AUTOMATIC</captureMethod>
      <inputSource class="participantPropertySource">
        <property>barcode</property>
      </inputSource>
    </input>

    <input id="last_name">
      <code>INPUT_PARTICIPANT_LAST_NAME</code>
      <dataType>TEXT</dataType>
      <captureMethod>AUTOMATIC</captureMethod>
      <inputSource class="participantPropertySource">
        <property>lastName</property>
      </inputSource>
    </input>

    <input id="first_name_in">
      <code>INPUT_PARTICIPANT_FIRST_NAME</code>
      <dataType>TEXT</dataType>
      <captureMethod>AUTOMATIC</captureMethod>
      <inputSource class="participantPropertySource">
        <property>firstName</property>
      </inputSource>
    </input>

    <input id="birth_date">
      <code>INPUT_PARTICIPANT_DATE_BIRTH</code>
      <dataType>DATE</dataType>
      <captureMethod>AUTOMATIC</captureMethod>
      <inputSource class="participantPropertySource">
        <property>birthDate</property>
      </inputSource>
    </input>

    <input id="gender">
      <code>INPUT_PARTICIPANT_GENDER</code>
      <dataType>TEXT</dataType>
      <captureMethod>AUTOMATIC</captureMethod>
      <inputSource class="participantPropertySource">
        <property>gender</property>
      </inputSource>
    </input>

    <input id="systolic_pressure">
      <code>INPUT_SYSTOLIC_PRESSURE</code>
      <measurementUnit>mmHg</measurementUnit>
      <dataType>INTEGER</dataType>
      <captureMethod>MANUAL</captureMethod>
      <inputSource class="outputParameterSource">
        <instrumentType>BloodPressure</instrumentType>
        <parameterName>CALC_AVG_SYSTOLIC_BP</parameterName>
      </inputSource>
    </input>

    <input id="diastolic_pressure">
      <code>INPUT_DIASTOLIC_PRESSURE</code>
      <measurementUnit>mmHg</measurementUnit>
      <dataType>INTEGER</dataType>
      <captureMethod>MANUAL</captureMethod>
      <inputSource class="outputParameterSource">
        <instrumentType>BloodPressure</instrumentType>
        <parameterName>CALC_AVG_DIASTOLIC_BP</parameterName>
      </inputSource>
    </input>

    <output id="PATIENT_ID">
      <vendorName>PATIENT_ID</vendorName>
      <code>OUTPUT_PARTICIPANT_BARCODE</code>
      <dataType>TEXT</dataType>
      <captureMethod>AUTOMATIC</captureMethod>
      <measurementUnit/>
      <integrityChecks>
        <equalsParameterCheck>
          <targetParameter reference="PATIENT_ID"/>
          <parameter reference="id"/>
          <customizedDescription>EqualsParameterCheck_Arterial_Stiffness</customizedDescription>
        </equalsParameterCheck>
      </integrityChecks>
    </output>

    <output id="FAM_NAME">
      <vendorName>FAM_NAME</vendorName>
      <code>OUTPUT_PARTICIPANT_LAST_NAME</code>
      <dataType>TEXT</dataType>
      <captureMethod>AUTOMATIC</captureMethod>
      <measurementUnit/>
      <integrityChecks>
        <equalsParameterCheck>
          <targetParameter reference="FAM_NAME"/>
          <parameter reference="last_name"/>
          <customizedDescription>EqualsParameterCheck_Arterial_Stiffness</customizedDescription>
        </equalsParameterCheck>
      </integrityChecks>
    </output>

    <output id="FIRST_NAME">
      <vendorName>FIRST_NAME</vendorName>
      <code>OUTPUT_PARTICIPANT_FIRST_NAME</code>
      <dataType>TEXT</dataType>
      <captureMethod>AUTOMATIC</captureMethod>
      <measurementUnit/>
      <integrityChecks>
        <equalsParameterCheck>
          <targetParameter reference="FIRST_NAME"/>
          <parameter reference="first_name_in"/>
          <customizedDescription>EqualsParameterCheck_Arterial_Stiffness</customizedDescription>
        </equalsParameterCheck>
      </integrityChecks>
    </output>
    
    <output id="DOB">
      <vendorName>DOB</vendorName>
      <code>OUTPUT_PARTICIPANT_DATE_BIRTH</code>
      <dataType>DATE</dataType>
      <captureMethod>AUTOMATIC</captureMethod>
      <measurementUnit/>
      <integrityChecks>
        <equalsParameterCheck>
          <targetParameter reference="DOB"/>
          <parameter reference="birth_date"/>
          <customizedDescription>EqualsParameterCheck_Arterial_Stiffness</customizedDescription>
        </equalsParameterCheck>
      </integrityChecks>
    </output>

    <output id="SEX">
      <vendorName>SEX</vendorName>
      <code>OUTPUT_PARTICIPANT_GENDER</code>
      <dataType>TEXT</dataType>
      <captureMethod>AUTOMATIC</captureMethod>
      <measurementUnit/>
      <integrityChecks>
        <equalsParameterCheck>
          <targetParameter reference="SEX"/>
          <parameter reference="gender"/>
          <customizedDescription>EqualsParameterCheck_Arterial_Stiffness</customizedDescription>
        </equalsParameterCheck>
      </integrityChecks>
    </output>

    <output id="SP">
      <vendorName>SP</vendorName>
      <code>OUTPUT_SYSTOLIC_PRESSURE</code>
      <dataType>INTEGER</dataType>
      <captureMethod>AUTOMATIC</captureMethod>
      <measurementUnit/>
      <integrityChecks>
        <equalsParameterCheck>
          <targetParameter reference="SP"/>
          <parameter reference="systolic_pressure"/>
          <customizedDescription>EqualsParameterCheck_Arterial_Stiffness</customizedDescription>
        </equalsParameterCheck>
      </integrityChecks>
    </output>

    <output id="DP">
      <vendorName>DP</vendorName>
      <code>OUTPUT_DIASTOLIC_PRESSURE</code>
      <dataType>INTEGER</dataType>
      <captureMethod>AUTOMATIC</captureMethod>
      <measurementUnit/>
      <integrityChecks>
        <equalsParameterCheck>
          <targetParameter reference="DP"/>
          <parameter reference="diastolic_pressure"/>
          <customizedDescription>EqualsParameterCheck_Arterial_Stiffness</customizedDescription>
        </equalsParameterCheck>
      </integrityChecks>
    </output>
    
    <output id="Peripheral_Pulse_Quality_Control_Pulse_Height">
      <vendorName>P_QC_PH</vendorName>
      <code>RES_PER_PULSE_QC_PULSE_HEIGHT</code>
      <dataType>DECIMAL</dataType>
      <captureMethod>AUTOMATIC</captureMethod>
    </output>

    <output id="Peripheral_Pulse_Quality_Control_Pulse_Height_Variation">
      <vendorName>P_QC_PHV</vendorName>
      <code>RES_PER_PULSE_QC_PULSE_HEIGHT_VAR</code>
      <dataType>DECIMAL</dataType>
      <captureMethod>AUTOMATIC</captureMethod>
    </output>

    <output id="Peripheral_Pulse_Quality_Control_Pulse_Length_Variation">
      <vendorName>P_QC_PLV</vendorName>
      <code>RES_PER_PULSE_QC_PULSE_LENGTH_VAR</code>
      <dataType>DECIMAL</dataType>
      <captureMethod>AUTOMATIC</captureMethod>
    </output>

    <output id="Peripheral_Pulse_Quality_Control_Diastolic_Variation">
      <vendorName>P_QC_DV</vendorName>
      <code>RES_PER_PULSE_QC_DIASTOLIC_VAR</code>
      <dataType>DECIMAL</dataType>
      <captureMethod>AUTOMATIC</captureMethod>
    </output>

    <output id="Peripheral_Systolic_Pressure">
      <vendorName>P_SP</vendorName>
      <code>RES_PER_SYSTOLIC_PRESSURE</code>
      <dataType>DECIMAL</dataType>
      <captureMethod>AUTOMATIC</captureMethod>
      <measurementUnit>mmHg</measurementUnit>
    </output>

    <output id="Peripheral_Diastolic_Pressure">
      <vendorName>P_DP</vendorName>
      <code>RES_PER_DIASTOLIC_PRESSURE</code>
      <dataType>DECIMAL</dataType>
      <captureMethod>AUTOMATIC</captureMethod>
      <measurementUnit>mmHg</measurementUnit>
    </output>
    
    <output id="Peripheral_Mean_Pressure">
      <vendorName>P_MEANP</vendorName>
      <code>RES_PER_MEAN_PRESSURE</code>
      <dataType>DECIMAL</dataType>
      <captureMethod>AUTOMATIC</captureMethod>
      <measurementUnit>mmHg</measurementUnit>
    </output>

    <output id="Peripheral_T1">
      <vendorName>P_T1</vendorName>
      <code>RES_PER_T1</code>
      <dataType>DECIMAL</dataType>
      <captureMethod>AUTOMATIC</captureMethod>
      <measurementUnit>ms</measurementUnit>
    </output>

    <output id="Peripheral_T2">
      <vendorName>P_T2</vendorName>
      <code>RES_PER_T2</code>
      <dataType>DECIMAL</dataType>
      <captureMethod>AUTOMATIC</captureMethod>
      <measurementUnit>ms</measurementUnit>
    </output>

    <output id="Peripheral_Augmentation_Index">
      <vendorName>P_AI</vendorName>
      <code>RES_PER_AUGMENTATION_INDEX</code>
      <dataType>DECIMAL</dataType>
      <captureMethod>AUTOMATIC</captureMethod>
      <measurementUnit>%</measurementUnit>
    </output>

    <output id="End_Systolic_Pressure">
      <vendorName>P_ESP</vendorName>
      <code>RES_END_SYSTOLIC_PRESSURE</code>
      <dataType>DECIMAL</dataType>
      <captureMethod>AUTOMATIC</captureMethod>
    </output>

    <output id="Peripheral_P1">
      <vendorName>P_P1</vendorName>
      <code>RES_PER_P1</code>
      <dataType>DECIMAL</dataType>
      <captureMethod>AUTOMATIC</captureMethod>
    </output>

    <output id="Peripheral_P2">
      <vendorName>P_P2</vendorName>
      <code>RES_PER_P2</code>
      <dataType>DECIMAL</dataType>
      <captureMethod>AUTOMATIC</captureMethod>
    </output>

    <output id="Peripheral_Confidence_Level_of_T1">
      <vendorName>P_QUALITY_T1</vendorName>
      <code>RES_PER_CONFIDENCE_LEVEL_T1</code>
      <dataType>INTEGER</dataType>
      <captureMethod>AUTOMATIC</captureMethod>
    </output>

    <output id="Peripheral_Confidence_Level_of_T2">
      <vendorName>P_QUALITY_T2</vendorName>
      <code>RES_PER_CONFIDENCE_LEVEL_T2</code>
      <dataType>INTEGER</dataType>
      <captureMethod>AUTOMATIC</captureMethod>
    </output>

    <output id="Central_Augmented_Pressure">
      <vendorName>C_AP</vendorName>
      <code>RES_CEN_AUGMENTED_PRESSURE</code>
      <dataType>DECIMAL</dataType>
      <captureMethod>AUTOMATIC</captureMethod>
      <measurementUnit>mmHg</measurementUnit>
    </output>

    <output id="Central_Mean_Pressure_of_Systole">
      <vendorName>C_MPS</vendorName>
      <code>RES_CEN_MEAN_PRESSURE_SYSTOLE</code>
      <dataType>DECIMAL</dataType>
      <captureMethod>AUTOMATIC</captureMethod>
      <measurementUnit>mmHg</measurementUnit>
    </output>

    <output id="Central_Mean_Pressure_of_Diastole">
      <vendorName>C_MPD</vendorName>
      <code>RES_CEN_MEAN_PRESSURE_DIASTOLE</code>
      <dataType>DECIMAL</dataType>
      <captureMethod>AUTOMATIC</captureMethod>
      <measurementUnit>mmHg</measurementUnit>
    </output>

    <output id="Central_Tension_Time_Index">
      <vendorName>C_TTI</vendorName>
      <code>RES_CEN_TENSION_TIME_INDEX</code>
      <dataType>DECIMAL</dataType>
      <captureMethod>AUTOMATIC</captureMethod>
    </output>

    <output id="Central_Diastolic_Time_Index">
      <vendorName>C_DTI</vendorName>
      <code>RES_CEN_DIASTOLIC_TIME_INDEX</code>
      <dataType>DECIMAL</dataType>
      <captureMethod>AUTOMATIC</captureMethod>
    </output>

    <output id="Central_Buckberg_SubEndocardial_Viability_Ratio">
      <vendorName>C_SVI</vendorName>
      <code>RES_CEN_BUCKBERG_SUBE_VIABILITY_RATIO</code>
      <dataType>DECIMAL</dataType>
      <captureMethod>AUTOMATIC</captureMethod>
      <measurementUnit>%</measurementUnit>
    </output>

    <output id="Augmentation_Load">
      <vendorName>C_AL</vendorName>
      <code>RES_AUGMENTATION_LOAD</code>
      <dataType>DECIMAL</dataType>
      <captureMethod>AUTOMATIC</captureMethod>
    </output>

    <output id="Augmentation_Time_Index">
      <vendorName>C_ATI</vendorName>
      <code>RES_AUGMENTATION_TIME_INDEX</code>
      <dataType>DECIMAL</dataType>
      <captureMethod>AUTOMATIC</captureMethod>
    </output>

    <output id="Heart_Rate">
      <vendorName>HR</vendorName>
      <code>RES_HEART_RATE</code>
      <dataType>DECIMAL</dataType>
      <captureMethod>AUTOMATIC</captureMethod>
      <measurementUnit>bmp</measurementUnit>
    </output>

    <output id="Central_Pulse_Period">
      <vendorName>C_PERIOD</vendorName>
      <code>RES_CEN_PULSE_PERIOD</code>
      <dataType>DECIMAL</dataType>
      <captureMethod>AUTOMATIC</captureMethod>
      <measurementUnit>ms</measurementUnit>
    </output>

    <output id="Central_Diastolic_Duration">
      <vendorName>C_DD</vendorName>
      <code>RES_CEN_DIASTOLIC_DURATION</code>
      <dataType>DECIMAL</dataType>
      <captureMethod>AUTOMATIC</captureMethod>
    </output>

    <output id="Central_ED_Period_Percent_Ejection_duration">
      <vendorName>C_ED_PERIOD</vendorName>
      <code>RES_CEN_ED_PERIOD_PERCENT_EJECT_DUR</code>
      <dataType>DECIMAL</dataType>
      <captureMethod>AUTOMATIC</captureMethod>
      <measurementUnit>%</measurementUnit>
    </output>

    <output id="Period_ED_Period_Percent">
      <vendorName>C_DD_PERIOD</vendorName>
      <code>RES_PERIOD_ED_PERIOD_PERCENT</code>
      <dataType>DECIMAL</dataType>
      <captureMethod>AUTOMATIC</captureMethod>
    </output>

    <output id="Central_Pulse_Height">
      <vendorName>C_PH</vendorName>
      <code>RES_CEN_PULSE_HEIGHT</code>
      <dataType>DECIMAL</dataType>
      <captureMethod>AUTOMATIC</captureMethod>
      <measurementUnit>mmHg</measurementUnit>
    </output>

    <output id="Central_Aug_PH_Percent">
      <vendorName>C_AGPH</vendorName>
      <code>RES_CEN_AUG_PH_PERCENT</code>
      <dataType>DECIMAL</dataType>
      <captureMethod>AUTOMATIC</captureMethod>
      <measurementUnit>%</measurementUnit>
    </output>

    <output id="Central_Pressure_at_T1_Dp">
      <vendorName>C_P1_HEIGHT</vendorName>
      <code>RES_CEN_PRESSURE_AT_T1_DP</code>
      <dataType>DECIMAL</dataType>
      <captureMethod>AUTOMATIC</captureMethod>
      <measurementUnit>%</measurementUnit>
    </output>

    <output id="Time_of_the_Start_of_the_Reflected_Wave">
      <vendorName>C_T1R</vendorName>
      <code>RES_TIME_START_REFLECTED_WAVE</code>
      <dataType>DECIMAL</dataType>
      <captureMethod>AUTOMATIC</captureMethod>
      <measurementUnit>ms</measurementUnit>
    </output>

    <output id="Central_Systolic_Pressure">
      <vendorName>C_SP</vendorName>
      <code>RES_CEN_SYSTOLIC_PRESSURE</code>
      <dataType>DECIMAL</dataType>
      <captureMethod>AUTOMATIC</captureMethod>
      <measurementUnit>mmHg</measurementUnit>
    </output>

    <output id="Central_Diastolic_Pressure">
      <vendorName>C_DP</vendorName>
      <code>RES_CEN_DIASTOLIC_PRESSURE</code>
      <dataType>DECIMAL</dataType>
      <captureMethod>AUTOMATIC</captureMethod>
      <measurementUnit>mmHg</measurementUnit>
    </output>

    <output id="Central_Mean_Pressure">
      <vendorName>C_MEANP</vendorName>
      <code>RES_CEN_MEAN_PRESSURE</code>
      <dataType>DECIMAL</dataType>
      <captureMethod>AUTOMATIC</captureMethod>
    </output>

    <output id="Central_T1">
      <vendorName>C_T1</vendorName>
      <code>RES_CEN_T1</code>
      <dataType>DECIMAL</dataType>
      <captureMethod>AUTOMATIC</captureMethod>
      <measurementUnit>ms</measurementUnit>
    </output>

    <output id="Central_T2">
      <vendorName>C_T2</vendorName>
      <code>RES_CEN_T2</code>
      <dataType>DECIMAL</dataType>
      <captureMethod>AUTOMATIC</captureMethod>
      <measurementUnit>ms</measurementUnit>
    </output>

    <output id="Central_Augmentation_Index">
      <vendorName>C_AI</vendorName>
      <code>RES_CEN_AUGMENTATION_INDEX</code>
      <dataType>DECIMAL</dataType>
      <captureMethod>AUTOMATIC</captureMethod>
    </output>

    <output id="Central_End_Systolic_Pressure">
      <vendorName>C_ESP</vendorName>
      <code>RES_CEN_END_SYSTOLIC_PRESSURE</code>
      <dataType>DECIMAL</dataType>
      <captureMethod>AUTOMATIC</captureMethod>
      <measurementUnit>mmHg</measurementUnit>
    </output>

    <output id="Central_Pressure_at_T1">
      <vendorName>C_P1</vendorName>
      <code>RES_CEN_PRESSURE_AT_T1</code>
      <dataType>DECIMAL</dataType>
      <captureMethod>AUTOMATIC</captureMethod>
      <measurementUnit>mmHg</measurementUnit>
    </output>

    <output id="Central_Pressure_at_T2">
      <vendorName>C_P2</vendorName>
      <code>RES_CEN_PRESSURE_AT_T2</code>
      <dataType>DECIMAL</dataType>
      <captureMethod>AUTOMATIC</captureMethod>
      <measurementUnit>mmHg</measurementUnit>
    </output>

    <output id="Central_T1_ED_Percent">
      <vendorName>C_T1ED</vendorName>
      <code>RES_CEN_T1_ED_PERCENT</code>
      <dataType>DECIMAL</dataType>
      <captureMethod>AUTOMATIC</captureMethod>
      <measurementUnit>mmHg</measurementUnit>
    </output>

    <output id="Central_T2_ED_Percent">
      <vendorName>C_T2ED</vendorName>
      <code>RES_CEN_T2_ED_PERCENT</code>
      <dataType>DECIMAL</dataType>
      <captureMethod>AUTOMATIC</captureMethod>
      <measurementUnit>mmHg</measurementUnit>
    </output>

    <output id="Central_Confidence_Level_of_T1">
      <vendorName>C_QUALITY_T1</vendorName>
      <code>RES_CEN_CONFIDENCE_LEVEL_T1</code>
      <dataType>INTEGER</dataType>
      <captureMethod>AUTOMATIC</captureMethod>
    </output>

    <output id="Central_Confidence_Level_of_T2">
      <vendorName>C_QUALITY_T2</vendorName>
      <code>RES_CEN_CONFIDENCE_LEVEL_T2</code>
      <dataType>INTEGER</dataType>
      <captureMethod>AUTOMATIC</captureMethod>
    </output>

    <output id="Operator_Index">
      <vendorName>P_QC_OTHER4</vendorName>
      <code>RES_OPERATOR_INDEX</code>
      <dataType>DECIMAL</dataType>
      <captureMethod>AUTOMATIC</captureMethod>
    </output>
  </instrumentParameters>
  
</instrumentType>
