<?xml version="1.0" encoding="ISO-8859-1"?>
<instrumentType>
  <name>ECG</name>

  <instruments>
    <instrument>
      <name>ECG 1</name>
      <vendor>GE</vendor>
      <model>CardioSoft</model>
      <serialNumber>1234567890</serialNumber>
      <barcode>ecg1</barcode>
      <status>ACTIVE</status>
    </instrument>
  </instruments>

  <!-- <contraindications>(removed)
   <contraIndication>
      <code>Other_CI</code>
      <requiresDescription>true</requiresDescription>
      <type>OBSERVED</type>
    </contraIndication>
  </contraindications> -->

  <instrumentParameters>
    <input id="id_in">
      <code>INPUT_PARTICIPANT_BARCODE</code>
      <dataType>TEXT</dataType>
      <captureMethod>AUTOMATIC</captureMethod>
      <inputSource class="participantPropertySource">
        <property>barcode</property>
      </inputSource>
    </input>

    <input id="last_name_in">
      <code>INPUT_PARTICIPANT_LAST_NAME</code>
      <dataType>TEXT</dataType>
      <captureMethod>AUTOMATIC</captureMethod>
      <inputSource class="participantPropertySource">
        <property>lastName</property>
      </inputSource>
    </input>

    <input id="first_name_in">
      <code>INPUT_PARTICIPANT_FIRST_NAME</code>
      <dataType>TEXT</dataType>
      <captureMethod>AUTOMATIC</captureMethod>
      <inputSource class="participantPropertySource">
        <property>firstName</property>
      </inputSource>
    </input>

    <input id="birth_year_in">
      <code>INPUT_PARTICIPANT_BIRTH_YEAR</code>
      <dataType>INTEGER</dataType>
      <captureMethod>AUTOMATIC</captureMethod>
      <inputSource class="participantPropertySource">
        <property>birthYear</property>
      </inputSource>
    </input>

    <input id="birth_month_in">
      <code>INPUT_PARTICIPANT_BIRTH_MONTH</code>
      <dataType>INTEGER</dataType>
      <captureMethod>AUTOMATIC</captureMethod>
      <inputSource class="participantPropertySource">
        <property>birthMonth</property>
      </inputSource>
    </input>

    <input id="birth_day_in">
      <code>INPUT_PARTICIPANT_BIRTH_DAY</code>
      <dataType>INTEGER</dataType>
      <captureMethod>AUTOMATIC</captureMethod>
      <inputSource class="participantPropertySource">
        <property>birthDay</property>
      </inputSource>
    </input>

    <input id="gender_in">
      <code>INPUT_PARTICIPANT_GENDER</code>
      <dataType>TEXT</dataType>
      <captureMethod>AUTOMATIC</captureMethod>
      <inputSource class="participantPropertySource">
        <property>gender</property>
      </inputSource>
    </input>

    <input id="ethnic_group_in">
      <code>INPUT_PARTICIPANT_ETHNIC_GROUP</code>
      <dataType>TEXT</dataType>
      <captureMethod>AUTOMATIC</captureMethod>
      <inputSource class="fixedSource">
        <value>CAUCASIAN</value>
      </inputSource>
    </input>

    <input id="pacemaker_in">
      <code>INPUT_PARTICIPANT_PACEMAKER</code>
      <dataType>INTEGER</dataType>
      <captureMethod>AUTOMATIC</captureMethod>
      <inputSource class="fixedSource">
        <value>0</value>
      </inputSource>
    </input>

    <input id="height_in">
      <code>INPUT_PARTICIPANT_HEIGHT</code>
      <measurementUnit>cm</measurementUnit>
      <dataType>INTEGER</dataType>
      <captureMethod>AUTOMATIC</captureMethod>
      <inputSource class="outputParameterSource">
        <instrumentType>StandingHeight</instrumentType>
        <parameterName>CALC_AVG_HEIGHT</parameterName>
      </inputSource>
    </input>

    <input id="weight_in">
      <code>INPUT_PARTICIPANT_WEIGHT</code>
      <measurementUnit>hg</measurementUnit>
      <dataType>INTEGER</dataType>
      <captureMethod>AUTOMATIC</captureMethod>
      <inputSource class="multipleOutputParameterSource">
        <outputParameterSourceList>
          <outputParameterSource>
            <instrumentType>Impedence310</instrumentType>
            <parameterName>RES_WEIGHT</parameterName>
          </outputParameterSource>
          <outputParameterSource>
            <instrumentType>Impedence418</instrumentType>
            <parameterName>RES_WEIGHT</parameterName>
          </outputParameterSource>
          <outputParameterSource>
            <instrumentType>Weight</instrumentType>
            <parameterName>RES_WEIGHT</parameterName>
          </outputParameterSource>
        </outputParameterSourceList>
      </inputSource>
    </input>

    <output id="participantID">
      <vendorName>participantID</vendorName>
      <code>OUTPUT_PARTICIPANT_BARCODE</code>
      <dataType>TEXT</dataType>
      <captureMethod>AUTOMATIC</captureMethod>
      <measurementUnit />
      <integrityChecks>
        <equalsParameterCheck>
          <targetParameter reference="participantID" />
          <parameter reference="id_in" />
          <customizedDescription>EqualsParameterCheck_ECG</customizedDescription>
        </equalsParameterCheck>
      </integrityChecks>
    </output>

    <output id="participantLastName">
      <vendorName>participantLastName</vendorName>
      <code>OUTPUT_PARTICIPANT_LAST_NAME</code>
      <dataType>TEXT</dataType>
      <captureMethod>AUTOMATIC</captureMethod>
      <measurementUnit />
      <integrityChecks>
        <equalsParameterCheck>
          <targetParameter reference="participantLastName" />
          <parameter reference="last_name_in" />
          <customizedDescription>EqualsParameterCheck_ECG</customizedDescription>
        </equalsParameterCheck>
      </integrityChecks>
    </output>

    <output id="Participant_First_Name">
      <vendorName>participantFirstName</vendorName>
      <code>OUTPUT_PARTICIPANT_FIRST_NAME</code>
      <dataType>TEXT</dataType>
      <captureMethod>AUTOMATIC</captureMethod>
      <measurementUnit />
      <integrityChecks>
        <equalsParameterCheck>
          <targetParameter reference="Participant_First_Name" />
          <parameter reference="first_name_in" />
          <customizedDescription>EqualsParameterCheck_ECG</customizedDescription>
        </equalsParameterCheck>
      </integrityChecks>
    </output>

    <output id="Participant_Birth_Day">
      <vendorName>participantBirthDay</vendorName>
      <code>OUTPUT_PARTICIPANT_BIRTH_DAY</code>
      <dataType>INTEGER</dataType>
      <captureMethod>AUTOMATIC</captureMethod>
      <measurementUnit />
      <integrityChecks>
        <equalsParameterCheck>
          <targetParameter reference="Participant_Birth_Day" />
          <parameter reference="birth_day_in" />
          <customizedDescription>EqualsParameterCheck_ECG</customizedDescription>
        </equalsParameterCheck>
      </integrityChecks>
    </output>

    <output id="participantBirthMonth">
      <vendorName>participantBirthMonth</vendorName>
      <code>OUTPUT_PARTICIPANT_BIRTH_MONTH</code>
      <dataType>INTEGER</dataType>
      <captureMethod>AUTOMATIC</captureMethod>
      <measurementUnit />
      <integrityChecks>
        <equalsParameterCheck>
          <targetParameter reference="participantBirthMonth" />
          <parameter reference="birth_month_in" />
          <customizedDescription>EqualsParameterCheck_ECG</customizedDescription>
        </equalsParameterCheck>
      </integrityChecks>
    </output>

    <output id="participantBirthYear">
      <vendorName>participantBirthYear</vendorName>
      <code>OUTPUT_PARTICIPANT_BIRTH_YEAR</code>
      <dataType>INTEGER</dataType>
      <captureMethod>AUTOMATIC</captureMethod>
      <measurementUnit />
      <integrityChecks>
        <equalsParameterCheck>
          <targetParameter reference="participantBirthYear" />
          <parameter reference="birth_year_in" />
          <customizedDescription>EqualsParameterCheck_ECG</customizedDescription>
        </equalsParameterCheck>
      </integrityChecks>
    </output>

    <output id="participantGender">
      <vendorName>participantGender</vendorName>
      <code>OUTPUT_PARTICIPANT_GENDER</code>
      <dataType>TEXT</dataType>
      <captureMethod>AUTOMATIC</captureMethod>
      <measurementUnit />
      <integrityChecks>
        <equalsParameterCheck>
          <targetParameter reference="participantGender" />
          <parameter reference="gender_in" />
          <customizedDescription>EqualsParameterCheck_ECG</customizedDescription>
        </equalsParameterCheck>
      </integrityChecks>
    </output>

    <output id="participantRace">
      <vendorName>participantRace</vendorName>
      <code>OUTPUT_PARTICIPANT_ETHNIC_GROUP</code>
      <dataType>TEXT</dataType>
      <captureMethod>AUTOMATIC</captureMethod>
      <measurementUnit />
      <integrityChecks>
        <equalsParameterCheck>
          <targetParameter reference="participantRace" />
          <parameter reference="ethnic_group_in" />
          <customizedDescription>EqualsParameterCheck_ECG</customizedDescription>
        </equalsParameterCheck>
      </integrityChecks>
    </output>

    <output id="participantHeight">
      <vendorName>participantHeight</vendorName>
      <code>OUTPUT_PARTICIPANT_HEIGHT</code>
      <dataType>INTEGER</dataType>
      <captureMethod>AUTOMATIC</captureMethod>
      <measurementUnit>cm</measurementUnit>
    </output>

    <output id="participantWeight">
      <vendorName>participantWeight</vendorName>
      <code>OUTPUT_PARTICIPANT_WEIGHT</code>
      <dataType>DECIMAL</dataType>
      <captureMethod>AUTOMATIC</captureMethod>
      <measurementUnit>kg</measurementUnit>
    </output>

    <output id="participantPacemaker">
      <vendorName>participantPacemaker</vendorName>
      <code>OUTPUT_PARTICIPANT_PACEMAKER</code>
      <dataType>INTEGER</dataType>
      <captureMethod>AUTOMATIC</captureMethod>
      <measurementUnit />
      <integrityChecks>
        <equalsParameterCheck>
          <targetParameter reference="participantPacemaker" />
          <parameter reference="pacemaker_in" />
          <customizedDescription>EqualsParameterCheck_ECG</customizedDescription>
        </equalsParameterCheck>
      </integrityChecks>
    </output>

    <output>
      <vendorName>time</vendorName>
      <code>RES_MEASUREMENT_TIME</code>
      <dataType>TEXT</dataType>
      <captureMethod>AUTOMATIC</captureMethod>
    </output>

    <output>
      <vendorName>date</vendorName>
      <code>RES_MEASUREMENT_DATE</code>
      <dataType>TEXT</dataType>
      <captureMethod>AUTOMATIC</captureMethod>
    </output>

    <output>
      <vendorName>diagnosis</vendorName>
      <code>RES_DIAGNOSIS</code>
      <dataType>TEXT</dataType>
      <captureMethod>AUTOMATIC</captureMethod>
    </output>

    <output>
      <vendorName>filterSetting</vendorName>
      <code>RES_FILTER_SETTINGS</code>
      <dataType>TEXT</dataType>
      <captureMethod>AUTOMATIC</captureMethod>
    </output>

    <output>
      <vendorName>diagnosisVersion</vendorName>
      <code>RES_DIAGNOSIS_VERSION</code>
      <dataType>TEXT</dataType>
      <captureMethod>AUTOMATIC</captureMethod>
    </output>

    <output>
      <vendorName>ventricularRate</vendorName>
      <code>RES_VENTRICULAR_RATE</code>
      <dataType>INTEGER</dataType>
      <measurementUnit>BPM</measurementUnit>
      <captureMethod>AUTOMATIC</captureMethod>
    </output>

    <output>
      <vendorName>PQInterval</vendorName>
      <code>RES_PQ_INTERVAL</code>
      <dataType>INTEGER</dataType>
      <measurementUnit>ms</measurementUnit>
      <captureMethod>AUTOMATIC</captureMethod>
    </output>

    <output>
      <vendorName>PDuration</vendorName>
      <code>RES_P_DURATION</code>
      <dataType>INTEGER</dataType>
      <measurementUnit>ms</measurementUnit>
      <captureMethod>AUTOMATIC</captureMethod>
    </output>

    <output>
      <vendorName>QRsDuration</vendorName>
      <code>RES_QRS_DURATION</code>
      <dataType>INTEGER</dataType>
      <measurementUnit>ms</measurementUnit>
      <captureMethod>AUTOMATIC</captureMethod>
    </output>

    <output>
      <vendorName>QTInterval</vendorName>
      <code>RES_QT_INTERVAL</code>
      <dataType>INTEGER</dataType>
      <measurementUnit>ms</measurementUnit>
      <captureMethod>AUTOMATIC</captureMethod>
    </output>

    <output>
      <vendorName>QTCInterval</vendorName>
      <code>RES_QTC_INTERVAL</code>
      <dataType>INTEGER</dataType>
      <measurementUnit>ms</measurementUnit>
      <captureMethod>AUTOMATIC</captureMethod>
    </output>

    <output>
      <vendorName>RRInterval</vendorName>
      <code>RES_RR_INTERVAL</code>
      <dataType>INTEGER</dataType>
      <measurementUnit>ms</measurementUnit>
      <captureMethod>AUTOMATIC</captureMethod>
    </output>

    <output>
      <vendorName>PPInterval</vendorName>
      <code>RES_PP_INTERVAL</code>
      <dataType>INTEGER</dataType>
      <measurementUnit>ms</measurementUnit>
      <captureMethod>AUTOMATIC</captureMethod>
    </output>

    <output>
      <vendorName>PAxis</vendorName>
      <code>RES_P_AXIS</code>
      <dataType>INTEGER</dataType>
      <measurementUnit>degree</measurementUnit>
      <captureMethod>AUTOMATIC</captureMethod>
    </output>

    <output>
      <vendorName>RAxis</vendorName>
      <code>RES_R_AXIS</code>
      <dataType>INTEGER</dataType>
      <measurementUnit>degree</measurementUnit>
      <captureMethod>AUTOMATIC</captureMethod>
    </output>

    <output>
      <vendorName>TAxis</vendorName>
      <code>RES_T_AXIS</code>
      <dataType>INTEGER</dataType>
      <measurementUnit>degree</measurementUnit>
      <captureMethod>AUTOMATIC</captureMethod>
    </output>

    <output>
      <vendorName>QRSNum</vendorName>
      <code>RES_QRS_NUMBER</code>
      <dataType>INTEGER</dataType>
      <captureMethod>AUTOMATIC</captureMethod>
    </output>

    <output>
      <vendorName>POnset</vendorName>
      <code>RES_P_ONSET</code>
      <dataType>INTEGER</dataType>
      <measurementUnit>ms</measurementUnit>
      <captureMethod>AUTOMATIC</captureMethod>
    </output>

    <output>
      <vendorName>POffset</vendorName>
      <code>RES_P_OFFSET</code>
      <dataType>INTEGER</dataType>
      <measurementUnit>ms</measurementUnit>
      <captureMethod>AUTOMATIC</captureMethod>
    </output>

    <output>
      <vendorName>QOnset</vendorName>
      <code>RES_Q_ONSET</code>
      <dataType>INTEGER</dataType>
      <measurementUnit>ms</measurementUnit>
      <captureMethod>AUTOMATIC</captureMethod>
    </output>

    <output>
      <vendorName>QOffset</vendorName>
      <code>RES_Q_OFFSET</code>
      <dataType>INTEGER</dataType>
      <measurementUnit>ms</measurementUnit>
      <captureMethod>AUTOMATIC</captureMethod>
    </output>

    <output>
      <vendorName>TOffset</vendorName>
      <code>RES_T_OFFSET</code>
      <dataType>INTEGER</dataType>
      <measurementUnit>ms</measurementUnit>
      <captureMethod>AUTOMATIC</captureMethod>
    </output>

    <output>
      <vendorName>xmlFile</vendorName>
      <code>RES_XML_FILE</code>
      <dataType>DATA</dataType>
      <captureMethod>AUTOMATIC</captureMethod>
    </output>

    <output>
      <vendorName>pdfFile</vendorName>
      <code>RES_PDF_FILE</code>
      <dataType>DATA</dataType>
      <captureMethod>AUTOMATIC</captureMethod>
    </output>
  </instrumentParameters>
</instrumentType>
